texthooker_proxy/__init__.py
texthooker_proxy/server.py
texthooker_proxy-0.1.0.dist-info/METADATA
texthooker_proxy-0.1.0.dist-info/WHEEL
texthooker_proxy-0.1.0.dist-info/entry_points.txt
texthooker_proxy-0.1.0.dist-info/top_level.txt
texthooker_proxy-0.1.0.dist-info/RECORD
