Metadata-Version: 2.4
Name: texthooker_proxy
Version: 0.1.0
Summary: Add your description here
Author-email: extremq <contact@extremq.com>
Project-URL: Homepage, https://github.com/extremq/texthooker_proxy
Requires-Python: >=3.13
Requires-Dist: websockets>=15.0.1
